apyhiveapi/__init__.py
apyhiveapi/action.py
apyhiveapi/alarm.py
apyhiveapi/camera.py
apyhiveapi/device_attributes.py
apyhiveapi/heating.py
apyhiveapi/hive.py
apyhiveapi/hotwater.py
apyhiveapi/hub.py
apyhiveapi/light.py
apyhiveapi/plug.py
apyhiveapi/sensor.py
apyhiveapi/session.py
apyhiveapi/api/__init__.py
apyhiveapi/api/hive_api.py
apyhiveapi/api/hive_async_api.py
apyhiveapi/api/hive_auth.py
apyhiveapi/api/hive_auth_async.py
apyhiveapi/data/alarm.json
apyhiveapi/data/camera.json
apyhiveapi/data/data.json
apyhiveapi/helper/__init__.py
apyhiveapi/helper/const.py
apyhiveapi/helper/debugger.py
apyhiveapi/helper/hive_exceptions.py
apyhiveapi/helper/hive_helper.py
apyhiveapi/helper/hivedataclasses.py
apyhiveapi/helper/logger.py
apyhiveapi/helper/map.py
pyhiveapi/__init__.py
pyhiveapi/action.py
pyhiveapi/alarm.py
pyhiveapi/camera.py
pyhiveapi/device_attributes.py
pyhiveapi/heating.py
pyhiveapi/hive.py
pyhiveapi/hotwater.py
pyhiveapi/hub.py
pyhiveapi/light.py
pyhiveapi/plug.py
pyhiveapi/sensor.py
pyhiveapi/session.py
pyhiveapi/api/__init__.py
pyhiveapi/api/hive_api.py
pyhiveapi/api/hive_async_api.py
pyhiveapi/api/hive_auth.py
pyhiveapi/api/hive_auth_async.py
pyhiveapi/helper/__init__.py
pyhiveapi/helper/const.py
pyhiveapi/helper/debugger.py
pyhiveapi/helper/hive_exceptions.py
pyhiveapi/helper/hive_helper.py
pyhiveapi/helper/hivedataclasses.py
pyhiveapi/helper/logger.py
pyhiveapi/helper/map.py
pyhiveapi-0.5.16.dist-info/LICENSE
pyhiveapi-0.5.16.dist-info/METADATA
pyhiveapi-0.5.16.dist-info/WHEEL
pyhiveapi-0.5.16.dist-info/top_level.txt
pyhiveapi-0.5.16.dist-info/RECORD
