Metadata-Version: 2.1
Name: pyhiveapi
Version: 0.5.16
Summary: A Python library to interface with the Hive API
Home-page: https://github.com/Pyhive/pyhiveapi
Author: Rendili
Author-email: rendili@outlook.com
License: MIT
Project-URL: Source, https://github.com/Pyhive/Pyhiveapi
Project-URL: Issue tracker, https://github.com/Pyhive/Pyhiveapi/issues
Keywords: Hive API Library
Classifier: Development Status :: 5 - Production/Stable
Classifier: Intended Audience :: Developers
Classifier: License :: OSI Approved :: MIT License
Classifier: Programming Language :: Python :: 3.6
Classifier: Programming Language :: Python :: 3.7
Classifier: Programming Language :: Python :: 3.8
Classifier: Programming Language :: Python :: 3.9
Requires-Python: >=3.6
License-File: LICENSE
Requires-Dist: pre-commit
Requires-Dist: boto3 >=1.16.10
Requires-Dist: botocore >=1.19.10
Requires-Dist: requests
Requires-Dist: aiohttp
Requires-Dist: pyquery
Requires-Dist: unasync
Requires-Dist: loguru
Provides-Extra: dev
Requires-Dist: tox ; extra == 'dev'
